opensearch_reindexer/__init__.py
opensearch_reindexer/base.py
opensearch_reindexer/db.py
opensearch_reindexer/helper.py
opensearch_reindexer-2.0.0.dist-info/entry_points.txt
opensearch_reindexer-2.0.0.dist-info/WHEEL
opensearch_reindexer-2.0.0.dist-info/METADATA
opensearch_reindexer-2.0.0.dist-info/RECORD
