Metadata-Version: 2.1
Name: opensearch-reindexer
Version: 2.0.0
Summary: `opensearch-reindex` is a Python library that serves to help streamline reindexing data from one OpenSearch index to another.
Home-page: https://github.com/Swiple/opensearch-reindexer
Author: Kenton Parton
Author-email: kparton@swiple.io
Requires-Python: >=3.9,<4.0
Classifier: Programming Language :: Python :: 3
Classifier: Programming Language :: Python :: 3.9
Classifier: Programming Language :: Python :: 3.10
Requires-Dist: opensearch-py (>=2.0.0,<3.0.0)
Requires-Dist: typer[all] (>=0.7.0,<0.8.0)
Project-URL: Repository, https://github.com/Swiple/opensearch-reindexer
